ojtool/__init__.py
ojtool/data.py
ojtool/ojtool.py
ojtool/utils.py
ojtool-0.1.5.dist-info/licenses/LICENSE
ojtool-0.1.5.dist-info/METADATA
ojtool-0.1.5.dist-info/WHEEL
ojtool-0.1.5.dist-info/top_level.txt
ojtool-0.1.5.dist-info/RECORD
