Metadata-Version: 2.4
Name: ojtool
Version: 0.1.5
Summary: Online Judge Test Data Generator.
Home-page: https://github.com/ElementCraft/python-ojtool
Author: elecraft
Author-email: elecraft@outlook.com
Project-URL: Bug Tracker, https://github.com/ElementCraft/python-ojtool/issues
Classifier: Programming Language :: Python :: 3
Classifier: License :: OSI Approved :: MIT License
Classifier: Operating System :: OS Independent
Requires-Python: >=3.6
License-File: LICENSE
Dynamic: author
Dynamic: author-email
Dynamic: classifier
Dynamic: description
Dynamic: description-content-type
Dynamic: home-page
Dynamic: license-file
Dynamic: project-url
Dynamic: requires-python
Dynamic: summary
